collective.elasticsearch-5.0.0-py3.8-nspkg.pth
collective/elasticsearch/__init__.py
collective/elasticsearch/configure.zcml
collective/elasticsearch/indexes.py
collective/elasticsearch/interfaces.py
collective/elasticsearch/local.py
collective/elasticsearch/manager.py
collective/elasticsearch/mapping.py
collective/elasticsearch/profiles.zcml
collective/elasticsearch/query.py
collective/elasticsearch/queueprocessor.py
collective/elasticsearch/result.py
collective/elasticsearch/setuphandlers.py
collective/elasticsearch/testing.py
collective/elasticsearch/upgrades.py
collective/elasticsearch/utils.py
collective/elasticsearch/browser/__init__.py
collective/elasticsearch/browser/configure.zcml
collective/elasticsearch/browser/controlpanel.py
collective/elasticsearch/browser/controlpanel_layout.pt
collective/elasticsearch/browser/search.py
collective/elasticsearch/browser/utilviews.py
collective/elasticsearch/patches/__init__.py
collective/elasticsearch/patches/configure.zcml
collective/elasticsearch/profiles/default/browserlayer.xml
collective/elasticsearch/profiles/default/controlpanel.xml
collective/elasticsearch/profiles/default/metadata.xml
collective/elasticsearch/profiles/default/registry.xml
collective/elasticsearch/profiles/uninstall/browserlayer.xml
collective/elasticsearch/services/__init__.py
collective/elasticsearch/services/configure.zcml
collective/elasticsearch/services/controlpanel.py
collective/elasticsearch/services/elasticsearch.py
collective/elasticsearch/tests/__init__.py
collective/elasticsearch/tests/test_processor.py
collective/elasticsearch/tests/test_search.py
collective/elasticsearch/tests/test_services.py
collective.elasticsearch-5.0.0.dist-info/LICENSE.GPL
collective.elasticsearch-5.0.0.dist-info/METADATA
collective.elasticsearch-5.0.0.dist-info/WHEEL
collective.elasticsearch-5.0.0.dist-info/entry_points.txt
collective.elasticsearch-5.0.0.dist-info/namespace_packages.txt
collective.elasticsearch-5.0.0.dist-info/top_level.txt
collective.elasticsearch-5.0.0.dist-info/RECORD
