Metadata-Version: 2.1
Name: collective.elasticsearch
Version: 5.0.0
Summary: elasticsearch integration with plone
Home-page: https://github.com/collective/collective.elasticsearch
Author: Nathan Van Gheem
Author-email: vangheem@gmail.com
License: GPL version 2
Project-URL: PyPI, https://pypi.python.org/pypi/collective.elasticsearch
Project-URL: Source, https://github.com/collective/collective.elasticsearch
Project-URL: Tracker, https://github.com/collective/collective.elasticsearch/issues
Keywords: plone elasticsearch search indexing
Classifier: Development Status :: 5 - Production/Stable
Classifier: Environment :: Web Environment
Classifier: Framework :: Plone :: 5.2
Classifier: Framework :: Plone :: 6.0
Classifier: Framework :: Plone :: Addon
Classifier: Framework :: Plone
Classifier: Framework :: Zope :: 4
Classifier: Framework :: Zope :: 5
Classifier: Intended Audience :: System Administrators
Classifier: License :: OSI Approved :: GNU General Public License (GPL)
Classifier: License :: OSI Approved :: GNU General Public License v2 (GPLv2)
Classifier: Operating System :: OS Independent
Classifier: Programming Language :: Python :: 3 :: Only
Classifier: Programming Language :: Python :: 3.7
Classifier: Programming Language :: Python :: 3.8
Classifier: Programming Language :: Python :: 3.9
Classifier: Programming Language :: Python :: 3.10
Classifier: Programming Language :: Python
Classifier: Topic :: Software Development :: Libraries :: Python Modules
Requires-Python: >=3.7
License-File: LICENSE.GPL
Requires-Dist: setuptools
Requires-Dist: elasticsearch (==7.7.0)
Requires-Dist: plone.app.registry
Requires-Dist: plone.api
Provides-Extra: test
Requires-Dist: plone.app.contentrules ; extra == 'test'
Requires-Dist: plone.app.contenttypes ; extra == 'test'
Requires-Dist: plone.restapi[test] ; extra == 'test'
Requires-Dist: plone.app.testing[robot] (>=7.0.0a3) ; extra == 'test'
Requires-Dist: plone.app.robotframework[test] (>=2.0.0a5) ; extra == 'test'
Requires-Dist: parameterized ; extra == 'test'
